seapdf/__init__.py
seapdf/seapdf.py
searchpdf/__init__.py
searchpdf/searchpdf.py
searchpdf-0.3.3.dist-info/DESCRIPTION.rst
searchpdf-0.3.3.dist-info/METADATA
searchpdf-0.3.3.dist-info/RECORD
searchpdf-0.3.3.dist-info/WHEEL
searchpdf-0.3.3.dist-info/entry_points.txt
searchpdf-0.3.3.dist-info/metadata.json
searchpdf-0.3.3.dist-info/top_level.txt
