Metadata-Version: 2.0
Name: searchpdf
Version: 0.3.3
Summary: converts non-searchable pdf files to searchable ones
Home-page: https://github.com/marpapad/searchpdf.git
Author: marpapad
Author-email: marypapadaki13@gmail.com
License: UNKNOWN
Download-URL: https://github.com/marpapad/searchpdf/archive/0.1.tar.gz
Platform: UNKNOWN
Classifier: Programming Language :: Python :: 3
Requires-Dist: Click
